{
    "partition": "Timestamp",
    "cluster": [
        "Label",
        "GPS",
        "Timestamp",
        "Source"
    ],
    "schema": [{
            "name": "Timestamp",
            "type": "TIMESTAMP",
            "mode": "NULLABLE"
        },
        {
            "name": "DeviceID",
            "type": "STRING",
            "mode": "NULLABLE"
        },
        {
            "name": "GPS",
            "type": "GEOGRAPHY",
            "mode": "NULLABLE"
        },
        {
            "name": "Elevation",
            "type": "FLOAT",
            "mode": "NULLABLE"
        },
        {
            "name": "PM1",
            "type": "FLOAT",
            "mode": "NULLABLE"
        },
        {
            "name": "PM2_5",
            "type": "FLOAT",
            "mode": "NULLABLE"
        },
        {
            "name": "PM10",
            "type": "FLOAT",
            "mode": "NULLABLE"
        },
        {
            "name": "Temperature",
            "type": "FLOAT",
            "mode": "NULLABLE"
        },
        {
            "name": "Humidity",
            "type": "FLOAT",
            "mode": "NULLABLE"
        },
        {
            "name": "MicsRED",
            "type": "INTEGER",
            "mode": "NULLABLE"
        },
        {
            "name": "MicsNOX",
            "type": "INTEGER",
            "mode": "NULLABLE"
        },
        {
            "name": "MicsHeater",
            "type": "BOOLEAN",
            "mode": "NULLABLE"
        },
        {
            "name": "RSSI",
            "type": "INTEGER",
            "mode": "NULLABLE"
        },
        {
            "name": "Source",
            "type": "STRING",
            "mode": "NULLABLE"
        },
        {
            "name": "PMSModel",
            "type": "STRING",
            "mode": "NULLABLE"
        },
        {
            "name": "Label",
            "type": "STRING",
            "mode": "NULLABLE"
        },
        {
            "name": "Flags",
            "type": "INTEGER",
            "mode": "NULLABLE"
        },
        {
            "name": "Pressure",
            "type": "FLOAT",
            "mode": "NULLABLE"
        },
        {
            "name": "PM2_5_Raw",
            "type": "FLOAT",
            "mode": "NULLABLE"
        },
        {
            "name": "CarbonMonoxide",
            "type": "FLOAT",
            "mode": "NULLABLE"
        },
        {
            "name": "NitrogenDioxide",
            "type": "FLOAT",
            "mode": "NULLABLE"
        },
        {
            "name": "Ozone",
            "type": "FLOAT",
            "mode": "NULLABLE"
        },
        {
            "name": "SulfurDioxide",
            "type": "FLOAT",
            "mode": "NULLABLE"
        }
    ]
}